<?xml version="1.0" encoding="UTF-8"?>
<Root>
  <PM_HEADER>
    <DONE_IRR>true</DONE_IRR>
  </PM_HEADER>
  <PARTIAL_MATRIX>
    <PARTIAL_DYN>
   0.000000000000000E+00   0.000000000000000E+00
   0.000000000000000E+00   0.000000000000000E+00
   0.000000000000000E+00   0.000000000000000E+00
   0.000000000000000E+00   0.000000000000000E+00
  -8.077531159348337E-09  -3.602568937521739E-08
   0.000000000000000E+00   0.000000000000000E+00
   0.000000000000000E+00   0.000000000000000E+00
   0.000000000000000E+00   0.000000000000000E+00
   0.000000000000000E+00   0.000000000000000E+00
   0.000000000000000E+00   0.000000000000000E+00
   1.198222101251971E+00  -1.316956973102992E+00
   0.000000000000000E+00   0.000000000000000E+00
   0.000000000000000E+00   0.000000000000000E+00
   0.000000000000000E+00   0.000000000000000E+00
   0.000000000000000E+00   0.000000000000000E+00
   0.000000000000000E+00   0.000000000000000E+00
   8.657926887637216E-02   7.348475455795678E-02
   0.000000000000000E+00   0.000000000000000E+00
   0.000000000000000E+00   0.000000000000000E+00
   0.000000000000000E+00   0.000000000000000E+00
   0.000000000000000E+00   0.000000000000000E+00
   0.000000000000000E+00   0.000000000000000E+00
  -6.854724488838869E-10  -2.597455550337259E-09
   0.000000000000000E+00   0.000000000000000E+00
   0.000000000000000E+00   0.000000000000000E+00
   0.000000000000000E+00   0.000000000000000E+00
   0.000000000000000E+00   0.000000000000000E+00
   0.000000000000000E+00   0.000000000000000E+00
  -1.880554245747438E+01   3.111041952165612E-05
   0.000000000000000E+00   0.000000000000000E+00
   0.000000000000000E+00   0.000000000000000E+00
   0.000000000000000E+00   0.000000000000000E+00
   0.000000000000000E+00   0.000000000000000E+00
   0.000000000000000E+00   0.000000000000000E+00
   1.134991882699283E-01   6.491520792567388E-04
   0.000000000000000E+00   0.000000000000000E+00
    </PARTIAL_DYN>
  </PARTIAL_MATRIX>
</Root>
