<?xml version="1.0" encoding="UTF-8"?>
<Root>
  <PM_HEADER>
    <DONE_IRR>true</DONE_IRR>
  </PM_HEADER>
  <PARTIAL_MATRIX>
    <PARTIAL_DYN>
   0.000000000000000E+00   0.000000000000000E+00
   0.000000000000000E+00   0.000000000000000E+00
   0.000000000000000E+00   0.000000000000000E+00
   6.104117027995424E-01   2.855878065309879E+00
   0.000000000000000E+00   0.000000000000000E+00
   0.000000000000000E+00   0.000000000000000E+00
   0.000000000000000E+00   0.000000000000000E+00
   0.000000000000000E+00   0.000000000000000E+00
   0.000000000000000E+00   0.000000000000000E+00
   2.687689930360206E-06   3.335098400125968E-05
   0.000000000000000E+00   0.000000000000000E+00
   0.000000000000000E+00   0.000000000000000E+00
   0.000000000000000E+00   0.000000000000000E+00
   0.000000000000000E+00   0.000000000000000E+00
   0.000000000000000E+00   0.000000000000000E+00
   8.653861110288549E-08   6.025561435176750E-08
   0.000000000000000E+00   0.000000000000000E+00
   0.000000000000000E+00   0.000000000000000E+00
   0.000000000000000E+00   0.000000000000000E+00
   0.000000000000000E+00   0.000000000000000E+00
   0.000000000000000E+00   0.000000000000000E+00
  -1.724840917173988E+01  -6.226436343360984E-06
   0.000000000000000E+00   0.000000000000000E+00
   0.000000000000000E+00   0.000000000000000E+00
   0.000000000000000E+00   0.000000000000000E+00
   0.000000000000000E+00   0.000000000000000E+00
   0.000000000000000E+00   0.000000000000000E+00
   3.519770465219394E-05   1.838738830353865E-06
   0.000000000000000E+00   0.000000000000000E+00
   0.000000000000000E+00   0.000000000000000E+00
   0.000000000000000E+00   0.000000000000000E+00
   0.000000000000000E+00   0.000000000000000E+00
   0.000000000000000E+00   0.000000000000000E+00
   1.608008727705804E-07  -7.518173244520750E-09
   0.000000000000000E+00   0.000000000000000E+00
   0.000000000000000E+00   0.000000000000000E+00
    </PARTIAL_DYN>
  </PARTIAL_MATRIX>
</Root>
